[{"Category": "BROADWAY MUSICALS", "Clues": [{"Question": "Based on a ballet, this 1944 musical begins at 6 A.M. in the Brooklyn Navy Yard", "Answer": "\\\"On the Town\\\""}], "Date": "7/14/1993"},{"Category": "FAMOUS AUTHORS", "Clues": [{"Question": "He used his fishing boat, the Pilar, for counter-intelligence work during World War I", "Answer": "Ernest Hemingway"}], "Date": "7/13/1993"},{"Category": "PHILANTHROPY", "Clues": [{"Question": "At the time of his death in 1937, he had given over $500 million to charity", "Answer": "John D. Rockefeller"}], "Date": "7/12/1993"},{"Category": "ACTRESSES & THEIR ROLES", "Clues": [{"Question": "In 1992 Angela Bassett played the Jacksons' mother on TV & Betty Shabazz in this film", "Answer": "Malcolm X"}], "Date": "7/9/1993"},{"Category": "WOMEN", "Clues": [{"Question": "Gloria Steinem, Susan Strasberg & Norman Mailer have all written books about her", "Answer": "Marilyn Monroe"}], "Date": "7/7/1993"},{"Category": "PRESIDENTIAL INAUGURATIONS", "Clues": [{"Question": "He used more words in his one inaugural address than FDR used in all four of his", "Answer": "William Henry Harrison"}], "Date": "7/6/1993"},{"Category": "FICTIONAL CHARACTERS", "Clues": [{"Question": "Chile's Juan Fernandez islands include a pair named for Alexander Selkirk & this fictional character", "Answer": "Robinson Crusoe"}], "Date": "7/5/1993"},{"Category": "LANGUAGES", "Clues": [{"Question": "Dublin's famous Book of Kells is written in this language", "Answer": "Latin"}], "Date": "7/2/1993"},{"Category": "BUSINESS & INDUSTRY", "Clues": [{"Question": "The Brooklyn Flint Glass Works changed its name to this after moving to a N.Y. town of the same name", "Answer": "Corning"}], "Date": "7/1/1993"},{"Category": "AMERICAN MUSICALS", "Clues": [{"Question": "A 1920s French production of this musical about 19th c. entertainers was titled \"Mississippi\"", "Answer": "Show Boat"}], "Date": "6/30/1993"},{"Category": "U.S. RIVERS", "Clues": [{"Question": "The name of this river, famous in song, may be a corruption of the Spanish for \"little Saint John\"", "Answer": "the Swanee"}], "Date": "6/29/1993"},{"Category": "GODS & GODDESSES", "Clues": [{"Question": "Augustus Caesar encouraged the worship of this god who was considered the avenger of Julius Caesar", "Answer": "Mars"}], "Date": "6/28/1993"},{"Category": "THE 50 STATES", "Clues": [{"Question": "Texas has the most farms with 185,000; this state has the fewest with about 500", "Answer": "Alaska"}], "Date": "6/22/1993"},{"Category": "SOUTH AMERICA", "Clues": [{"Question": "The name of this capital city is a corruption of Rimac, the river on which it lies", "Answer": "Lima, Peru"}], "Date": "6/18/1993"},{"Category": "PORT CITIES", "Clues": [{"Question": "In population, it was by far the largest city in the Confederacy at the start of the Civil War", "Answer": "New Orleans"}], "Date": "6/17/1993"},{"Category": "THE 1950s", "Clues": [{"Question": "June 2, 1953 event telecast worldwide & filmed in Technicolor", "Answer": "Queen Elizabeth II\\'s coronation"}], "Date": "6/16/1993"},{"Category": "19th CENTURY ELECTIONS", "Clues": [{"Question": "In 1836 Van Buren ran against Harrison for U.S. president & these 2 ran for president of Texas", "Answer": "Sam Houston & Stephen F. Austin"}], "Date": "6/7/1993"},{"Category": "MEN OF SCIENCE", "Clues": [{"Question": "In addition to a pendulum, Jean Foucault made a simple one of these to prove the Earth rotated", "Answer": "gyroscope"}], "Date": "5/27/1993"},{"Category": "POETRY", "Clues": [{"Question": "The woman with the most quotes in the new edition of Bartlett's Familiar Quotations is this American", "Answer": "Emily Dickinson"}], "Date": "5/21/1993"},{"Category": "HISTORIC NAMES", "Clues": [{"Question": "In 1529 this Spaniard was made Marques del Valle de Oaxaca", "Answer": "Hern\u00e1n Cort\u00e9s"}], "Date": "5/20/1993"},{"Category": "ANCIENT ROME", "Clues": [{"Question": "General Publius Scipio won the surname \"Africanus\" for beating this man at the 202 B.C. Battle of Zama", "Answer": "Hannibal"}], "Date": "5/14/1993"},{"Category": "WORLD CAPITALS", "Clues": [{"Question": "Roxas Boulevard in this capital city was formerly named Dewey Boulevard", "Answer": "Manila"}], "Date": "5/13/1993"},{"Category": "STATE CAPITALS", "Clues": [{"Question": "This city in the northwest is the \"City of Trees\"; its name comes from the French for \"wooded\"", "Answer": "Boise"}], "Date": "4/8/1993"},{"Category": "THE TONY AWARDS", "Clues": [{"Question": "He won his first of 9 Tonys for the first Broadway musical he choreographed, \"The Pajama Game\"", "Answer": "Bob Fosse"}], "Date": "4/2/1993"},{"Category": "EXPLORERS", "Clues": [{"Question": "This contemporary of Columbus established the concept of a New World in his 1504 letter \"Mundus Novus\"", "Answer": "Amerigo Vespucci"}], "Date": "4/1/1993"},{"Category": "MONARCHS", "Clues": [{"Question": "In 1942 she become the first reigning queen to address the U.S. Congress", "Answer": "Wilhelmina"}], "Date": "3/31/1993"},{"Category": "WORLD CITIES", "Clues": [{"Question": "The original full name of this Mexican port translates to \"Rich Town of the True Cross\"", "Answer": "Veracruz"}], "Date": "3/16/1993"},{"Category": "THE NOBEL PRIZE", "Clues": [{"Question": "The category in which the U.S. has won the fewest medals--10", "Answer": "Literature"}], "Date": "3/3/1993"},{"Category": "NOTABLE NAMES", "Clues": [{"Question": "Eugene Cernan is the last person to stand here", "Answer": "the Moon"}], "Date": "2/26/1993"},{"Category": "19th CENTURY AMERICA", "Clues": [{"Question": "The execution of this man & his followers in 1859 is believed to be the only one for treason against a state", "Answer": "John Brown"}], "Date": "2/25/1993"},{"Category": "MILITARY LEADERS", "Clues": [{"Question": "This U.S. general was born April 5, 1937 to parents who had emigrated from Jamaica", "Answer": "Colin Powell"}], "Date": "2/22/1993"},{"Category": "NEW ENGLAND", "Clues": [{"Question": "In Washington, D.C.'s Statuary Hall, the state of Vermont is represented by this patriot", "Answer": "Ethan Allen"}], "Date": "2/19/1993"},{"Category": "IN THE NEWS", "Clues": [{"Question": "Tennessee governor Ned McWherter chose Harlan Mathews to fill this man's Senate seat until 1994", "Answer": "Al Gore"}], "Date": "2/17/1993"},{"Category": "NEWSPAPERS", "Clues": [{"Question": "It was once advertised as \"The Daily Diary of the American Dream\"", "Answer": "The Wall Street Journal"}], "Date": "2/10/1993"},{"Category": "OPERA", "Clues": [{"Question": "This 20th century opera was inspired by Hieronymus Bosch's painting \"The Adoration of the Magi\"", "Answer": "Amahl and the Night Visitors"}], "Date": "2/5/1993"},{"Category": "OSCAR-WINNING FILMS", "Clues": [{"Question": "A series of articles about corruption in the longshoremen's union inspired this 1954 film", "Answer": "On the Waterfront"}], "Date": "2/4/1993"},{"Category": "BRITISH MONARCHS", "Clues": [{"Question": "1 of 4 British monarchs who reigns were longer than Elizabeth I's 45 years", "Answer": "(1 of) Victoria, Henry III, Edward III, & George III"}], "Date": "1/29/1993"},{"Category": "POLITICAL LEADERS", "Clues": [{"Question": "His books \"No Easy Walk to Freedom\" & \"The Struggle Is My Life\" were published during his imprisonment", "Answer": "Nelson Mandela"}], "Date": "1/19/1993"},{"Category": "U.S. LAKES", "Clues": [{"Question": "Wizard Island sits in this lake in what was once Mount Mazama", "Answer": "Crater Lake"}], "Date": "12/16/1992"},{"Category": "ANATOMY", "Clues": [{"Question": "You have this bone, snakes don't, & in bats, it's keeled", "Answer": "a breastbone (or sternum)"}], "Date": "12/15/1992"},{"Category": "ROMAN EMPERORS", "Clues": [{"Question": "In 54 A.D., as the result of his mother's scheming, he became the first teenage emperor of Rome at age 16", "Answer": "Nero"}], "Date": "12/14/1992"},{"Category": "TRANSPORTATION", "Clues": [{"Question": "Last names of the motor car maker & motor car dealer who merged in Manchester, England in 1906", "Answer": "Rolls & Royce"}], "Date": "12/11/1992"},{"Category": "FAMOUS NAMES", "Clues": [{"Question": "The last of his 56 children, Mabel Sanborn, died in 1950 at age 87", "Answer": "Brigham Young"}], "Date": "12/1/1992"},{"Category": "MUSICIANS", "Clues": [{"Question": "On his 1986 death he was called \"arguably the only white jazz player to be the best on his instrument\"", "Answer": "Benny Goodman"}], "Date": "11/30/1992"},{"Category": "ISLANDS", "Clues": [{"Question": "This is the largest island in the Indian Ocean", "Answer": "Madagascar"}], "Date": "11/27/1992"},{"Category": "THE CABINET", "Clues": [{"Question": "This cabinet department is in charge of printing all postage stamps", "Answer": "Treasury"}], "Date": "11/26/1992"},{"Category": "STATE CAPITALS", "Clues": [{"Question": "John Tyler, James Monroe & Jefferson Davis are buried in this capital's Hollywood Cemetery", "Answer": "Richmond, Virginia"}], "Date": "11/25/1992"},{"Category": "HISTORIC PAIRS", "Clues": [{"Question": "They were the maternal grandparents of England's Queen Mary I", "Answer": "Ferdinand & Isabella"}], "Date": "11/24/1992"},{"Category": "FICTIONAL CHARACTERS", "Clues": [{"Question": "He retired after the only woman he ever loved, opera singer Irene Adler, passed away", "Answer": "Sherlock Holmes"}], "Date": "11/23/1992"},{"Category": "PRESIDENTS' HOMES", "Clues": [{"Question": "The exterior of the governor's mansion in Florida is modeled after the home of this president", "Answer": "Andrew Jackson"}], "Date": "11/20/1992"},{"Category": "POETRY", "Clues": [{"Question": "William Blake called them \"The Two Contrary States of the Human Soul\" and wrote songs of them", "Answer": "innocence & experience"}], "Date": "11/19/1992"},{"Category": "WORLD DRAMA", "Clues": [{"Question": "Sophocles, Euripides & Eugene O'Neill all wrote plays with this woman's name in their titles", "Answer": "Electra"}], "Date": "11/18/1992"},{"Category": "NEWSPAPERS", "Clues": [{"Question": "It was first published between 1861 and 1865; it was revived in 1918; stopped in 1919, and revived again in 1942", "Answer": "Stars and Stripes"}], "Date": "11/17/1992"},{"Category": "COLLEGES & UNIVERSITIES", "Clues": [{"Question": "Henry Moore's sculpture, \"Nuclear Energy\", can be seen on the campus of this university", "Answer": "the University of Chicago"}], "Date": "11/16/1992"},{"Category": "THE AUTO INDUSTRY", "Clues": [{"Question": "This automaker's trademark symbolizes the 3 places where its engines were used: land, air & water", "Answer": "Mercedes-Benz"}], "Date": "11/13/1992"},{"Category": "POLAND", "Clues": [{"Question": "Laid to rest temporarily at Arlington in 1941, his remains were returned to Poland in 1992", "Answer": "Jan Paderewski"}], "Date": "11/12/1992"},{"Category": "VICE PRESIDENTS", "Clues": [{"Question": "He served as vice president for the shortest length of time: one month", "Answer": "John Tyler"}], "Date": "11/11/1992"},{"Category": "MYTHS & LEGENDS", "Clues": [{"Question": "What the ancient Greek writer Theseus called a \"monokeros\", we call this", "Answer": "a unicorn"}], "Date": "11/10/1992"},{"Category": "GEOGRAPHY", "Clues": [{"Question": "Since the breakup of the Soviet Union, this is the largest country in area in the world", "Answer": "Russia"}], "Date": "11/9/1992"},{"Category": "OPERETTAS", "Clues": [{"Question": "Sigmund Romberg wrote the music for this 1926 operetta inspired by an Arab revolt in French Morocco", "Answer": "The Desert Song"}], "Date": "11/6/1992"},{"Category": "AMERICAN HISTORY", "Clues": [{"Question": "His left arm is buried at Ellwood Farm near Fredericksburg, Virginia", "Answer": "Stonewall Jackson"}], "Date": "11/3/1992"},{"Category": "THE SUPREME COURT", "Clues": [{"Question": "The 1973 case Doe v. Bolton was decided with this more famous case", "Answer": "Roe v. Wade"}], "Date": "10/30/1992"},{"Category": "U.S. PRESIDENTS", "Clues": [{"Question": "The first two presidents not born in Virginia were born in what is now this state", "Answer": "Massachusetts"}], "Date": "10/29/1992"},{"Category": "U.S. STATES", "Clues": [{"Question": "This state with several hundred ghost towns was admitted to the Union on Halloween in 1864", "Answer": "Nevada"}], "Date": "10/28/1992"},{"Category": "WORD & PHRASE ORIGINS", "Clues": [{"Question": "This phrase meaning the aristocracy is derived from the part of a loaf served to honored guests", "Answer": "the upper crust"}], "Date": "10/27/1992"},{"Category": "HISTORIC NAMES", "Clues": [{"Question": "For his licentious behavior, monk Grigori Yefimovich Novykh earned this nickname meaning \"debauched one\"", "Answer": "Rasputin"}], "Date": "10/26/1992"},{"Category": "WORD ORIGINS", "Clues": [{"Question": "The name of this swift current between 2 of the Lofoten Islands off Norway has come to refer any whirlpool", "Answer": "a maelstrom"}], "Date": "10/19/1992"},{"Category": "RELIGIOUS GROUPS", "Clues": [{"Question": "\"The War Cry\" & \"The Young Soldier\" are publications of this religious movement", "Answer": "Salvation Army"}], "Date": "10/14/1992"},{"Category": "PRESIDENTS", "Clues": [{"Question": "Before Eisenhower, he was the last president to preside over the admission of a new state", "Answer": "(William Howard) Taft"}], "Date": "10/13/1992"},{"Category": "LANGUAGES", "Clues": [{"Question": "The 2 languages on the Rosetta Stone", "Answer": "Egyptian & Greek"}], "Date": "10/5/1992"},{"Category": "ENTERTAINERS OF THE PAST", "Clues": [{"Question": "This Missouri-born expatriate starred in the 1935 French film \"Princess Tam-Tam\"", "Answer": "Josephine Baker"}], "Date": "9/28/1992"},{"Category": "PSYCHOLOGY", "Clues": [{"Question": "In Freud's \"Interpretation of Dreams\", he mentions this king of Thebes", "Answer": "Oedipus"}], "Date": "9/15/1992"},{"Category": "POETRY", "Clues": [{"Question": "About her Tennyson wrote, \"She took the tax away and built herself an everlasting name\"", "Answer": "Lady Godiva"}], "Date": "9/14/1992"},{"Category": "SHIPS", "Clues": [{"Question": "This British navy ship left Devenport Dec. 27, 1831 & went around the world on a 5-year survey mission", "Answer": "the HMS Beagle"}], "Date": "9/10/1992"},{"Category": "FAMOUS SCIENTISTS", "Clues": [{"Question": "In 1969 the N.Y. Times retracted a 1920 editorial ridiculing his claim that rockets could fly to the Moon", "Answer": "Robert Goddard"}], "Date": "9/8/1992"},{"Category": "BUSINESS & INDUSTRY", "Clues": [{"Question": "This chain of 748 shoe stores was named for a Scottish professional golfer", "Answer": "Thom McAn"}], "Date": "9/7/1992"}]